Metadata-Version: 1.0
Name: final-distributions
Version: 1.8
Summary: Binomial & Gaussian distributions
Home-page: UNKNOWN
Author: Franklin Rivers
Author-email: letsT17@gmail.com
License: UNKNOWN
Platform: UNKNOWN
